README.txt
setup.py
baff/__init__.py
baff/api.py
baff/factory.py
baff/loop.py
baff/main.py
baff/tasks.py
baff.egg-info/PKG-INFO
baff.egg-info/SOURCES.txt
baff.egg-info/dependency_links.txt
baff.egg-info/not-zip-safe
baff.egg-info/top_level.txt